simple_static/__init__.py
simple_static/build.py
simple_static/plugins.py
simple_static/serve.py
simple_static/utils.py
simple_static-0.0.4.dist-info/LICENSE
simple_static-0.0.4.dist-info/METADATA
simple_static-0.0.4.dist-info/WHEEL
simple_static-0.0.4.dist-info/entry_points.txt
simple_static-0.0.4.dist-info/top_level.txt
simple_static-0.0.4.dist-info/RECORD
