Metadata-Version: 2.1
Name: simple-static
Version: 0.0.4
Summary: UNKNOWN
Home-page: UNKNOWN
License: UNKNOWN
Platform: UNKNOWN
License-File: LICENSE
Requires-Dist: Jinja2
Requires-Dist: MarkupSafe
Requires-Dist: PyYAML
